cleanode/__init__.py
cleanode/ode_solvers.py
third_party_libs/__init__.py
third_party_libs/table_it.py
cleanode-0.1.9.dist-info/LICENSE
cleanode-0.1.9.dist-info/METADATA
cleanode-0.1.9.dist-info/WHEEL
cleanode-0.1.9.dist-info/top_level.txt
cleanode-0.1.9.dist-info/RECORD
