Metadata-Version: 2.1
Name: cleanode
Version: 0.1.9
Summary: Example using an embedded solver
Home-page: https://github.com/vlakir/cleanode.git
Author: Vladimir Kirievskiy
Author-email: vlakir1234@gmail.com
License: UNKNOWN
Platform: UNKNOWN
Classifier: Programming Language :: Python :: 3.9
Classifier: License :: OSI Approved :: GNU General Public License v3 (GPLv3)
Classifier: Topic :: Scientific/Engineering
License-File: LICENSE
Requires-Dist: numpy (>=1.21.2)
Requires-Dist: funnydeco (>=0.1.5)
Requires-Dist: matplotlib (>=3.4.3)
Requires-Dist: scipy (>=1.7.1)
